pyserato/__init__.py
pyserato/builder.py
pyserato/py.typed
pyserato/util.py
pyserato/encoders/base_encoder.py
pyserato/encoders/serato_tags.py
pyserato/encoders/utils.py
pyserato/encoders/v1_mp3_encoder.py
pyserato/encoders/v2_mp3_encoder.py
pyserato/model/crate.py
pyserato/model/hot_cue.py
pyserato/model/hot_cue_type.py
pyserato/model/serato_color.py
pyserato/model/tempo.py
pyserato/model/track.py
pyserato-0.2.0.dist-info/licenses/LICENSE
pyserato-0.2.0.dist-info/METADATA
pyserato-0.2.0.dist-info/WHEEL
pyserato-0.2.0.dist-info/top_level.txt
pyserato-0.2.0.dist-info/RECORD
