Metadata-Version: 2.4
Name: pyserato
Version: 0.2.0
Summary: PySerato API.
Author-email: Luke Purnell <luke.a.purnell@gmail.com>
License-File: LICENSE
Requires-Dist: mutagen~=1.47
Provides-Extra: dev
Requires-Dist: mypy; extra == "dev"
Requires-Dist: flake8; extra == "dev"
Requires-Dist: black; extra == "dev"
Requires-Dist: coverage; extra == "dev"
Provides-Extra: test
Requires-Dist: pytest; extra == "test"
Requires-Dist: flake8>=6.1.0; extra == "test"
Requires-Dist: mypy; extra == "test"
Requires-Dist: coverage; extra == "test"
Provides-Extra: publish
Requires-Dist: build; extra == "publish"
Requires-Dist: twine; extra == "publish"
Requires-Dist: wheel; extra == "publish"
Requires-Dist: setuptools; extra == "publish"
Dynamic: license-file
